cve202221371/main.py
cve202221371/includes/__init__.py
cve202221371/includes/bot.py
cve202221371/includes/filereader.py
cve202221371/includes/scan.py
cve202221371/includes/writefile.py
cve202221371/utils/__init__.py
cve202221371/utils/configure.py
cve202221371/utils/const.py
cve202221371/utils/helpers.py
cve202221371/utils/status.py
CVE_2022_21371-0.0.4.dist-info/LICENSE
CVE_2022_21371-0.0.4.dist-info/METADATA
CVE_2022_21371-0.0.4.dist-info/WHEEL
CVE_2022_21371-0.0.4.dist-info/entry_points.txt
CVE_2022_21371-0.0.4.dist-info/top_level.txt
CVE_2022_21371-0.0.4.dist-info/RECORD
