Metadata-Version: 2.1
Name: CVE-2022-21371
Version: 0.0.4
Author: @karthi-the-hacker
Author-email: contact@cappriciosec.com
License: MIT
License-File: LICENSE
